{
  "mainLine": {
    "id": 1,
    "stations": [
      {
        "id": 1,
        "name": "神戸三宮"
      },
      {
        "id": 2,
        "name": "尼崎"
      },
      {
        "id": 3,
        "name": "難波"
      },
      {
        "id": 4,
        "name": "近鉄日本橋"
      },
      {
        "id": 5,
        "name": "大阪上本町"
      },
      {
        "id": 6,
        "name": "鶴橋"
      },
      {
        "id": 7,
        "name": "今里"
      },
      {
        "id": 8,
        "name": "布施"
      },
      {
        "id": 9,
        "name": "河内永和"
      },
      {
        "id": 10,
        "name": "河内小阪"
      },
      {
        "id": 11,
        "name": "八戸ノ里"
      },
      {
        "id": 12,
        "name": "若江岩田"
      },
      {
        "id": 13,
        "name": "河内花園"
      },
      {
        "id": 14,
        "name": "東花園"
      },
      {
        "id": 15,
        "name": "瓢箪山"
      },
      {
        "id": 16,
        "name": "枚岡"
      },
      {
        "id": 17,
        "name": "額田"
      },
      {
        "id": 18,
        "name": "石切"
      },
      {
        "id": 19,
        "name": "生駒"
      },
      {
        "id": 20,
        "name": "東生駒"
      },
      {
        "id": 21,
        "name": "富雄"
      },
      {
        "id": 22,
        "name": "学園前"
      },
      {
        "id": 23,
        "name": "菖蒲池"
      },
      {
        "id": 24,
        "name": "大和西大寺"
      },
      {
        "id": 25,
        "name": "新大宮"
      },
      {
        "id": 26,
        "name": "近鉄奈良"
      }
    ]
  },
  "subLines": [
    {
      "id": 2,
      "stations": [
        {
          "id": 101,
          "name": "コスモスクエア"
        },
        {
          "id": 102,
          "name": "大阪港"
        },
        {
          "id": 103,
          "name": "朝潮橋"
        },
        {
          "id": 104,
          "name": "弁天町"
        },
        {
          "id": 105,
          "name": "九条"
        },
        {
          "id": 106,
          "name": "阿波座"
        },
        {
          "id": 107,
          "name": "本町"
        },
        {
          "id": 108,
          "name": "堺筋本町"
        },
        {
          "id": 109,
          "name": "谷町四丁目"
        },
        {
          "id": 110,
          "name": "森ノ宮"
        },
        {
          "id": 111,
          "name": "緑橋"
        },
        {
          "id": 112,
          "name": "深江橋"
        },
        {
          "id": 113,
          "name": "高井戸"
        },
        {
          "id": 114,
          "name": "長田"
        },
        {
          "id": 115,
          "name": "荒本"
        },
        {
          "id": 116,
          "name": "吉田"
        },
        {
          "id": 117,
          "name": "新石切"
        },
        {
          "id": 19,
          "name": "生駒"
        }
      ],
      "xPos": -6
    },
    {
      "id": 3,
      "stations": [
        {
          "id": 19,
          "name": "生駒"
        },
        {
          "id": 201,
          "name": "白庭台"
        },
        {
          "id": 202,
          "name": "学研北生駒"
        },
        {
          "id": 203,
          "name": "登美ケ丘"
        }
      ],
      "xPos": -8
    }
  ],
  "trains": [
    {
      "stations": [
        1,
        2,
        3,
        4,
        5,
        6,
        19,
        22,
        24,
        25,
        26
      ],
      "speed": 5,
      "count": 3
    },
    {
      "stations": [
        3,
        4,
        5,
        6,
        8,
        18,
        19,
        22,
        24,
        25,
        26
      ],
      "speed": 4,
      "count": 3
    },
    {
      "stations": [
        2,
        3,
        4,
        5,
        6,
        8,
        10,
        14,
        15,
        16,
        17,
        18,
        19,
        20,
        21,
        22,
        23,
        24
      ],
      "speed": 2,
      "count": 3
    },
    {
      "stations": [
        3,
        4,
        5,
        6,
        7,
        8,
        9,
        10,
        11,
        12,
        13,
        14,
        15,
        16,
        17,
        18,
        19,
        20,
        21,
        22,
        23,
        24
      ],
      "speed": 1,
      "count": 3
    },
    {
      "stations": [
        2,
        3,
        4,
        5,
        6,
        7,
        8,
        9,
        10,
        11,
        12,
        13,
        14
      ],
      "speed": 1,
      "count": 3
    },
    {
      "stations": [
        101,
        102,
        103,
        104,
        105,
        106,
        107,
        108,
        109,
        110,
        111,
        112,
        113,
        114,
        115,
        116,
        117,
        19,
        201,
        202,
        203
      ],
      "speed": 1,
      "count": 4
    },
    {
      "stations": [
        101,
        102,
        103,
        104,
        105,
        106,
        107,
        108,
        109,
        110,
        111,
        112,
        113,
        114,
        115,
        116,
        117,
        19
      ],
      "speed": 1,
      "count": 4
    }
  ],
  "title": "近鉄奈良線",
  "author": "ponkotuy"
}
